{"numTotalTestSuites":4,"numPassedTestSuites":4,"numFailedTestSuites":0,"numPendingTestSuites":0,"numTotalTests":48,"numPassedTests":48,"numFailedTests":0,"numPendingTests":0,"numTodoTests":0,"snapshot":{"added":0,"failure":false,"filesAdded":0,"filesRemoved":0,"filesRemovedList":[],"filesUnmatched":0,"filesUpdated":0,"matched":0,"total":0,"unchecked":0,"uncheckedKeysByFile":[],"unmatched":0,"updated":0,"didUpdate":false},"startTime":1775258096887,"success":true,"testResults":[{"assertionResults":[{"ancestorTitles":["Exercício 01"],"fullName":"Exercício 01 Ex01 - Válida - Questão 1","status":"passed","title":"Ex01 - Válida - Questão 1","duration":3.7149279999999862,"failureMessages":[],"meta":{}},{"ancestorTitles":["Exercício 01"],"fullName":"Exercício 01 Ex01 - Correta - Questão 1","status":"passed","title":"Ex01 - Correta - Questão 1","duration":0.7284609999999816,"failureMessages":[],"meta":{}},{"ancestorTitles":["Exercício 01"],"fullName":"Exercício 01 Ex01 - Válida - Questão 2","status":"passed","title":"Ex01 - Válida - Questão 2","duration":0.45730099999997265,"failureMessages":[],"meta":{}},{"ancestorTitles":["Exercício 01"],"fullName":"Exercício 01 Ex01 - Correta - Questão 2","status":"passed","title":"Ex01 - Correta - Questão 2","duration":0.8508820000000128,"failureMessages":[],"meta":{}},{"ancestorTitles":["Exercício 01"],"fullName":"Exercício 01 Ex01 - Válida - Questão 3","status":"passed","title":"Ex01 - Válida - Questão 3","duration":0.4884959999999978,"failureMessages":[],"meta":{}},{"ancestorTitles":["Exercício 01"],"fullName":"Exercício 01 Ex01 - Correta - Questão 3","status":"passed","title":"Ex01 - Correta - Questão 3","duration":0.3095609999999738,"failureMessages":[],"meta":{}},{"ancestorTitles":["Exercício 01"],"fullName":"Exercício 01 Ex01 - Válida - Questão 4","status":"passed","title":"Ex01 - Válida - Questão 4","duration":0.5341950000000111,"failureMessages":[],"meta":{}},{"ancestorTitles":["Exercício 01"],"fullName":"Exercício 01 Ex01 - Correta - Questão 4","status":"passed","title":"Ex01 - Correta - Questão 4","duration":0.4846780000000308,"failureMessages":[],"meta":{}},{"ancestorTitles":["Exercício 01"],"fullName":"Exercício 01 Ex01 - Válida - Questão 5","status":"passed","title":"Ex01 - Válida - Questão 5","duration":1.0222160000000144,"failureMessages":[],"meta":{}},{"ancestorTitles":["Exercício 01"],"fullName":"Exercício 01 Ex01 - Correta - Questão 5","status":"passed","title":"Ex01 - Correta - Questão 5","duration":0.45561399999996866,"failureMessages":[],"meta":{}},{"ancestorTitles":["Exercício 01"],"fullName":"Exercício 01 Ex01 - Válida - Questão 6","status":"passed","title":"Ex01 - Válida - Questão 6","duration":0.3609819999999786,"failureMessages":[],"meta":{}},{"ancestorTitles":["Exercício 01"],"fullName":"Exercício 01 Ex01 - Correta - Questão 6","status":"passed","title":"Ex01 - Correta - Questão 6","duration":0.2434470000000033,"failureMessages":[],"meta":{}},{"ancestorTitles":["Exercício 01"],"fullName":"Exercício 01 Ex01 - Válida - Questão 7","status":"passed","title":"Ex01 - Válida - Questão 7","duration":0.3034139999999752,"failureMessages":[],"meta":{}},{"ancestorTitles":["Exercício 01"],"fullName":"Exercício 01 Ex01 - Correta - Questão 7","status":"passed","title":"Ex01 - Correta - Questão 7","duration":0.23881699999998318,"failureMessages":[],"meta":{}},{"ancestorTitles":["Exercício 01"],"fullName":"Exercício 01 Ex01 - Válida - Questão 8","status":"passed","title":"Ex01 - Válida - Questão 8","duration":0.3146899999999846,"failureMessages":[],"meta":{}},{"ancestorTitles":["Exercício 01"],"fullName":"Exercício 01 Ex01 - Correta - Questão 8","status":"passed","title":"Ex01 - Correta - Questão 8","duration":0.23747900000000755,"failureMessages":[],"meta":{}},{"ancestorTitles":["Exercício 01"],"fullName":"Exercício 01 Ex01 - Válida - Questão 9","status":"passed","title":"Ex01 - Válida - Questão 9","duration":0.3126020000000267,"failureMessages":[],"meta":{}},{"ancestorTitles":["Exercício 01"],"fullName":"Exercício 01 Ex01 - Correta - Questão 9","status":"passed","title":"Ex01 - Correta - Questão 9","duration":0.3754040000000032,"failureMessages":[],"meta":{}},{"ancestorTitles":["Exercício 01"],"fullName":"Exercício 01 Ex01 - Válida - Questão 10","status":"passed","title":"Ex01 - Válida - Questão 10","duration":0.3260789999999929,"failureMessages":[],"meta":{}},{"ancestorTitles":["Exercício 01"],"fullName":"Exercício 01 Ex01 - Correta - Questão 10","status":"passed","title":"Ex01 - Correta - Questão 10","duration":0.24650800000000572,"failureMessages":[],"meta":{}}],"startTime":1775258097246,"endTime":1775258097259.3262,"status":"passed","message":"","name":"/home/vicmca/CodeProjects/School/materiais/atv_pub/3c-04-listas/ex01.test.js"},{"assertionResults":[{"ancestorTitles":["Exercício 02"],"fullName":"Exercício 02 Ex02 - Válida - Questão 1","status":"passed","title":"Ex02 - Válida - Questão 1","duration":3.64702699999998,"failureMessages":[],"meta":{}},{"ancestorTitles":["Exercício 02"],"fullName":"Exercício 02 Ex02 - Correta - Questão 1","status":"passed","title":"Ex02 - Correta - Questão 1","duration":0.7056410000000142,"failureMessages":[],"meta":{}},{"ancestorTitles":["Exercício 02"],"fullName":"Exercício 02 Ex02 - Válida - Questão 2","status":"passed","title":"Ex02 - Válida - Questão 2","duration":0.4788130000000024,"failureMessages":[],"meta":{}},{"ancestorTitles":["Exercício 02"],"fullName":"Exercício 02 Ex02 - Correta - Questão 2","status":"passed","title":"Ex02 - Correta - Questão 2","duration":0.8651270000000295,"failureMessages":[],"meta":{}},{"ancestorTitles":["Exercício 02"],"fullName":"Exercício 02 Ex02 - Válida - Questão 3","status":"passed","title":"Ex02 - Válida - Questão 3","duration":0.5369370000000231,"failureMessages":[],"meta":{}},{"ancestorTitles":["Exercício 02"],"fullName":"Exercício 02 Ex02 - Correta - Questão 3","status":"passed","title":"Ex02 - Correta - Questão 3","duration":0.343037000000038,"failureMessages":[],"meta":{}},{"ancestorTitles":["Exercício 02"],"fullName":"Exercício 02 Ex02 - Válida - Questão 4","status":"passed","title":"Ex02 - Válida - Questão 4","duration":0.5699070000000006,"failureMessages":[],"meta":{}},{"ancestorTitles":["Exercício 02"],"fullName":"Exercício 02 Ex02 - Correta - Questão 4","status":"passed","title":"Ex02 - Correta - Questão 4","duration":0.5252479999999764,"failureMessages":[],"meta":{}},{"ancestorTitles":["Exercício 02"],"fullName":"Exercício 02 Ex02 - Válida - Questão 5","status":"passed","title":"Ex02 - Válida - Questão 5","duration":1.0447570000000042,"failureMessages":[],"meta":{}},{"ancestorTitles":["Exercício 02"],"fullName":"Exercício 02 Ex02 - Correta - Questão 5","status":"passed","title":"Ex02 - Correta - Questão 5","duration":0.4524420000000191,"failureMessages":[],"meta":{}},{"ancestorTitles":["Exercício 02"],"fullName":"Exercício 02 Ex02 - Válida - Questão 6","status":"passed","title":"Ex02 - Válida - Questão 6","duration":0.35571899999996504,"failureMessages":[],"meta":{}},{"ancestorTitles":["Exercício 02"],"fullName":"Exercício 02 Ex02 - Correta - Questão 6","status":"passed","title":"Ex02 - Correta - Questão 6","duration":0.2433489999999665,"failureMessages":[],"meta":{}},{"ancestorTitles":["Exercício 02"],"fullName":"Exercício 02 Ex02 - Válida - Questão 7","status":"passed","title":"Ex02 - Válida - Questão 7","duration":0.3039099999999735,"failureMessages":[],"meta":{}},{"ancestorTitles":["Exercício 02"],"fullName":"Exercício 02 Ex02 - Correta - Questão 7","status":"passed","title":"Ex02 - Correta - Questão 7","duration":0.23910000000000764,"failureMessages":[],"meta":{}},{"ancestorTitles":["Exercício 02"],"fullName":"Exercício 02 Ex02 - Válida - Questão 8","status":"passed","title":"Ex02 - Válida - Questão 8","duration":0.3097759999999994,"failureMessages":[],"meta":{}},{"ancestorTitles":["Exercício 02"],"fullName":"Exercício 02 Ex02 - Correta - Questão 8","status":"passed","title":"Ex02 - Correta - Questão 8","duration":0.24380800000000136,"failureMessages":[],"meta":{}},{"ancestorTitles":["Exercício 02"],"fullName":"Exercício 02 Ex02 - Válida - Questão 9","status":"passed","title":"Ex02 - Válida - Questão 9","duration":0.3228719999999612,"failureMessages":[],"meta":{}},{"ancestorTitles":["Exercício 02"],"fullName":"Exercício 02 Ex02 - Correta - Questão 9","status":"passed","title":"Ex02 - Correta - Questão 9","duration":0.4006820000000175,"failureMessages":[],"meta":{}},{"ancestorTitles":["Exercício 02"],"fullName":"Exercício 02 Ex02 - Válida - Questão 10","status":"passed","title":"Ex02 - Válida - Questão 10","duration":0.3434090000000083,"failureMessages":[],"meta":{}},{"ancestorTitles":["Exercício 02"],"fullName":"Exercício 02 Ex02 - Correta - Questão 10","status":"passed","title":"Ex02 - Correta - Questão 10","duration":0.21398300000004156,"failureMessages":[],"meta":{}},{"ancestorTitles":["Exercício 02"],"fullName":"Exercício 02 Ex02 - Válida - Questão 11","status":"passed","title":"Ex02 - Válida - Questão 11","duration":0.19308599999999387,"failureMessages":[],"meta":{}},{"ancestorTitles":["Exercício 02"],"fullName":"Exercício 02 Ex02 - Correta - Questão 11","status":"passed","title":"Ex02 - Correta - Questão 11","duration":0.1344029999999634,"failureMessages":[],"meta":{}},{"ancestorTitles":["Exercício 02"],"fullName":"Exercício 02 Ex02 - Válida - Questão 12","status":"passed","title":"Ex02 - Válida - Questão 12","duration":0.16654800000003434,"failureMessages":[],"meta":{}},{"ancestorTitles":["Exercício 02"],"fullName":"Exercício 02 Ex02 - Correta - Questão 12","status":"passed","title":"Ex02 - Correta - Questão 12","duration":0.1271160000000009,"failureMessages":[],"meta":{}},{"ancestorTitles":["Exercício 02"],"fullName":"Exercício 02 Ex02 - Válida - Questão 13","status":"passed","title":"Ex02 - Válida - Questão 13","duration":0.16566100000000006,"failureMessages":[],"meta":{}},{"ancestorTitles":["Exercício 02"],"fullName":"Exercício 02 Ex02 - Correta - Questão 13","status":"passed","title":"Ex02 - Correta - Questão 13","duration":0.19342000000000326,"failureMessages":[],"meta":{}},{"ancestorTitles":["Exercício 02"],"fullName":"Exercício 02 Ex02 - Válida - Questão 14","status":"passed","title":"Ex02 - Válida - Questão 14","duration":0.28073100000000295,"failureMessages":[],"meta":{}},{"ancestorTitles":["Exercício 02"],"fullName":"Exercício 02 Ex02 - Correta - Questão 14","status":"passed","title":"Ex02 - Correta - Questão 14","duration":0.22366199999999026,"failureMessages":[],"meta":{}}],"startTime":1775258097250,"endTime":1775258097265.2236,"status":"passed","message":"","name":"/home/vicmca/CodeProjects/School/materiais/atv_pub/3c-04-listas/ex02.test.js"}]}