{"numTotalTestSuites":3,"numPassedTestSuites":2,"numFailedTestSuites":1,"numPendingTestSuites":0,"numTotalTests":20,"numPassedTests":20,"numFailedTests":0,"numPendingTests":0,"numTodoTests":0,"snapshot":{"added":0,"failure":false,"filesAdded":0,"filesRemoved":0,"filesRemovedList":[],"filesUnmatched":0,"filesUpdated":0,"matched":0,"total":0,"unchecked":0,"uncheckedKeysByFile":[],"unmatched":0,"updated":0,"didUpdate":false},"startTime":1773882304670,"success":false,"testResults":[{"assertionResults":[{"ancestorTitles":["Exercício 01"],"fullName":"Exercício 01 Ex01 - Válida - Questão 1","status":"passed","title":"Ex01 - Válida - Questão 1","duration":4.25019199999997,"failureMessages":[],"meta":{}},{"ancestorTitles":["Exercício 01"],"fullName":"Exercício 01 Ex01 - Correta - Questão 1","status":"passed","title":"Ex01 - Correta - Questão 1","duration":0.7480189999999993,"failureMessages":[],"meta":{}},{"ancestorTitles":["Exercício 01"],"fullName":"Exercício 01 Ex01 - Válida - Questão 2","status":"passed","title":"Ex01 - Válida - Questão 2","duration":0.41944199999988996,"failureMessages":[],"meta":{}},{"ancestorTitles":["Exercício 01"],"fullName":"Exercício 01 Ex01 - Correta - Questão 2","status":"passed","title":"Ex01 - Correta - Questão 2","duration":0.8281840000000784,"failureMessages":[],"meta":{}},{"ancestorTitles":["Exercício 01"],"fullName":"Exercício 01 Ex01 - Válida - Questão 3","status":"passed","title":"Ex01 - Válida - Questão 3","duration":0.47464800000000196,"failureMessages":[],"meta":{}},{"ancestorTitles":["Exercício 01"],"fullName":"Exercício 01 Ex01 - Correta - Questão 3","status":"passed","title":"Ex01 - Correta - Questão 3","duration":0.27997000000004846,"failureMessages":[],"meta":{}},{"ancestorTitles":["Exercício 01"],"fullName":"Exercício 01 Ex01 - Válida - Questão 4","status":"passed","title":"Ex01 - Válida - Questão 4","duration":0.5172390000000178,"failureMessages":[],"meta":{}},{"ancestorTitles":["Exercício 01"],"fullName":"Exercício 01 Ex01 - Correta - Questão 4","status":"passed","title":"Ex01 - Correta - Questão 4","duration":0.4218559999999343,"failureMessages":[],"meta":{}},{"ancestorTitles":["Exercício 01"],"fullName":"Exercício 01 Ex01 - Válida - Questão 5","status":"passed","title":"Ex01 - Válida - Questão 5","duration":0.8203509999999596,"failureMessages":[],"meta":{}},{"ancestorTitles":["Exercício 01"],"fullName":"Exercício 01 Ex01 - Correta - Questão 5","status":"passed","title":"Ex01 - Correta - Questão 5","duration":0.38238799999999173,"failureMessages":[],"meta":{}},{"ancestorTitles":["Exercício 01"],"fullName":"Exercício 01 Ex01 - Válida - Questão 6","status":"passed","title":"Ex01 - Válida - Questão 6","duration":0.331784999999968,"failureMessages":[],"meta":{}},{"ancestorTitles":["Exercício 01"],"fullName":"Exercício 01 Ex01 - Correta - Questão 6","status":"passed","title":"Ex01 - Correta - Questão 6","duration":0.1888450000000148,"failureMessages":[],"meta":{}},{"ancestorTitles":["Exercício 01"],"fullName":"Exercício 01 Ex01 - Válida - Questão 7","status":"passed","title":"Ex01 - Válida - Questão 7","duration":0.24548399999991943,"failureMessages":[],"meta":{}},{"ancestorTitles":["Exercício 01"],"fullName":"Exercício 01 Ex01 - Correta - Questão 7","status":"passed","title":"Ex01 - Correta - Questão 7","duration":0.16592000000002827,"failureMessages":[],"meta":{}},{"ancestorTitles":["Exercício 01"],"fullName":"Exercício 01 Ex01 - Válida - Questão 8","status":"passed","title":"Ex01 - Válida - Questão 8","duration":0.23616900000001806,"failureMessages":[],"meta":{}},{"ancestorTitles":["Exercício 01"],"fullName":"Exercício 01 Ex01 - Correta - Questão 8","status":"passed","title":"Ex01 - Correta - Questão 8","duration":0.1693000000000211,"failureMessages":[],"meta":{}},{"ancestorTitles":["Exercício 01"],"fullName":"Exercício 01 Ex01 - Válida - Questão 9","status":"passed","title":"Ex01 - Válida - Questão 9","duration":0.2303630000000112,"failureMessages":[],"meta":{}},{"ancestorTitles":["Exercício 01"],"fullName":"Exercício 01 Ex01 - Correta - Questão 9","status":"passed","title":"Ex01 - Correta - Questão 9","duration":0.28796599999998307,"failureMessages":[],"meta":{}},{"ancestorTitles":["Exercício 01"],"fullName":"Exercício 01 Ex01 - Válida - Questão 10","status":"passed","title":"Ex01 - Válida - Questão 10","duration":0.25672099999997045,"failureMessages":[],"meta":{}},{"ancestorTitles":["Exercício 01"],"fullName":"Exercício 01 Ex01 - Correta - Questão 10","status":"passed","title":"Ex01 - Correta - Questão 10","duration":0.21721400000001267,"failureMessages":[],"meta":{}}],"startTime":1773882305406,"endTime":1773882305419.2173,"status":"passed","message":"","name":"/home/vicmca/CodeProjects/School/materiais/atividades/3c-04-listas/ex01.test.js"},{"assertionResults":[],"startTime":1773882304670,"endTime":1773882304670,"status":"failed","message":"pedras02 is not defined","name":"/home/vicmca/CodeProjects/School/materiais/atividades/3c-04-listas/ex02.test.js"}]}